agc.py
agc-0.0.5.dist-info/LICENSE
agc-0.0.5.dist-info/METADATA
agc-0.0.5.dist-info/WHEEL
agc-0.0.5.dist-info/top_level.txt
agc-0.0.5.dist-info/RECORD
