Metadata-Version: 2.1
Name: agc
Version: 0.0.5
Summary: Python code to compute and plot (truncated, weighted) area under gain curves (agc)
Home-page: https://github.com/ftheberge/agc
Author: François Théberge
Author-email: theberge@ieee.org
License: MIT
Platform: UNKNOWN
Classifier: Development Status :: 4 - Beta
Classifier: License :: OSI Approved :: MIT License
Classifier: Programming Language :: Python
Classifier: Programming Language :: Python :: 3
Classifier: Topic :: Scientific/Engineering
Classifier: Topic :: Software Development :: Libraries :: Python Modules
Classifier: Intended Audience :: Science/Research
Requires-Python: >=3.6
License-File: LICENSE
Requires-Dist: numpy
Requires-Dist: pandas
Requires-Dist: scipy
